azure/mixedreality/authentication/__init__.py
azure/mixedreality/authentication/_client.py
azure/mixedreality/authentication/_utils.py
azure/mixedreality/authentication/_version.py
azure/mixedreality/authentication/_generated/__init__.py
azure/mixedreality/authentication/_generated/_configuration.py
azure/mixedreality/authentication/_generated/_mixed_reality_sts_rest_client.py
azure/mixedreality/authentication/_generated/aio/__init__.py
azure/mixedreality/authentication/_generated/aio/_configuration.py
azure/mixedreality/authentication/_generated/aio/_mixed_reality_sts_rest_client.py
azure/mixedreality/authentication/_generated/aio/operations/__init__.py
azure/mixedreality/authentication/_generated/aio/operations/_mixed_reality_sts_rest_client_operations.py
azure/mixedreality/authentication/_generated/models/__init__.py
azure/mixedreality/authentication/_generated/models/_models.py
azure/mixedreality/authentication/_generated/models/_models_py3.py
azure/mixedreality/authentication/_generated/operations/__init__.py
azure/mixedreality/authentication/_generated/operations/_mixed_reality_sts_rest_client_operations.py
azure/mixedreality/authentication/_shared/__init__.py
azure/mixedreality/authentication/_shared/authentication_endpoint.py
azure/mixedreality/authentication/_shared/mixed_reality_token_credential.py
azure/mixedreality/authentication/_shared/mixedreality_account_key_credential.py
azure/mixedreality/authentication/_shared/static_access_token_credential.py
azure/mixedreality/authentication/_shared/aio/__init__.py
azure/mixedreality/authentication/_shared/aio/mixed_reality_token_credential.py
azure/mixedreality/authentication/_shared/aio/mixedreality_account_key_credential.py
azure/mixedreality/authentication/_shared/aio/static_access_token_credential.py
azure/mixedreality/authentication/aio/__init__.py
azure/mixedreality/authentication/aio/_client_async.py
azure_mixedreality_authentication-1.0.0b1.dist-info/LICENSE.txt
azure_mixedreality_authentication-1.0.0b1.dist-info/METADATA
azure_mixedreality_authentication-1.0.0b1.dist-info/WHEEL
azure_mixedreality_authentication-1.0.0b1.dist-info/top_level.txt
azure_mixedreality_authentication-1.0.0b1.dist-info/RECORD
