Metadata-Version: 2.1
Name: azure-mixedreality-authentication
Version: 1.0.0b1
Summary: Microsoft Azure Mixed Reality Authentication Client Library for Python
Home-page: https://github.com/Azure/azure-sdk-for-python
Author: Microsoft Corporation
Author-email: azuresdkengsysadmins@microsoft.com
License: MIT License
Project-URL: Bug Reports, https://github.com/Azure/azure-sdk-for-python/issues
Project-URL: Source, https://github.com/Azure/azure-sdk-python
Platform: UNKNOWN
Classifier: Development Status :: 4 - Beta
Classifier: Programming Language :: Python
Classifier: Programming Language :: Python :: 2
Classifier: Programming Language :: Python :: 2.7
Classifier: Programming Language :: Python :: 3
Classifier: Programming Language :: Python :: 3.5
Classifier: Programming Language :: Python :: 3.6
Classifier: Programming Language :: Python :: 3.7
Classifier: Programming Language :: Python :: 3.8
Classifier: Programming Language :: Python :: 3.9
Classifier: License :: OSI Approved :: MIT License
Requires-Dist: azure-core (<2.0.0,>=1.4.0)
Requires-Dist: msrest (>=0.5.0)
Requires-Dist: azure-mixedreality-nspkg ; python_version<'3.0'
Requires-Dist: typing ; python_version<'3.5'
